django_hv/__init__.py
django_hv/fields.py
django_hv/forms.py
django_hv/http.py
django_hv/middleware.py
django_hv/utils.py
django_hv/widgets.py
django_hv/templates/django_hv/forms/label.xml
django_hv/templates/django_hv/forms/view.xml
django_hv/templates/django_hv/forms/widgets/attrs.xml
django_hv/templates/django_hv/forms/widgets/date-field.xml
django_hv/templates/django_hv/forms/widgets/option.xml
django_hv/templates/django_hv/forms/widgets/picker-field.xml
django_hv/templates/django_hv/forms/widgets/picker-item.xml
django_hv/templates/django_hv/forms/widgets/select-multiple.xml
django_hv/templates/django_hv/forms/widgets/select-single.xml
django_hv/templates/django_hv/forms/widgets/switch.xml
django_hv/templates/django_hv/forms/widgets/text-field.xml
django_hv/templatetags/__init__.py
django_hv/templatetags/hv_tags.py
django_hyperview-0.0.2.dist-info/METADATA
django_hyperview-0.0.2.dist-info/WHEEL
django_hyperview-0.0.2.dist-info/top_level.txt
django_hyperview-0.0.2.dist-info/RECORD
