Metadata-Version: 2.1
Name: django-hyperview
Version: 0.0.2
Summary: Django extensions for Hyperview mobile apps
Author-email: Rami <ramiboutas@protonmail.com>
Project-URL: Homepage, https://github.com/ramiboutas/django-hyperview
Project-URL: Bug Tracker, https://github.com/ramiboutas/django-hyperview/issues
Classifier: Development Status :: 4 - Beta
Classifier: Programming Language :: Python :: 3
Classifier: License :: OSI Approved :: MIT License
Classifier: Operating System :: OS Independent
Classifier: Intended Audience :: Developers
Requires-Python: >=3.7
Requires-Dist: django
